{"name":"Augustus Wynn","tagline":"My personal site","body":"### Welcome To my Site\r\n\r\n\r\n### What I do\r\nI am candidate for a BSE in Computer Engineering at the University of Pennsylvania.\r\nI think all computation in interesting, from systems to high abstractions.\r\nI also love American Sign Language.\r\n\r\n### Contact\r\nMy github is here: @github\r\nEmail(s):\r\nguswynn AT gmail DOT com\r\nwyna AT seas DOT upenn DOT com\r\n\r\n### Links\r\n[Resume](/resume.pdf)\r\n[LinkedIn](https://www.linkedin.com/in/augustus-wynn-24428491)\r\n\r\n","google":"","note":"Don't delete this file! It's used internally to help with page regeneration."}
